fframelesswindow/__init__.py
fframelesswindow/_rc/__init__.py
fframelesswindow/_rc/resource.py
fframelesswindow/linux/__init__.py
fframelesswindow/linux/window_effect.py
fframelesswindow/mac/__init__.py
fframelesswindow/mac/window_effect.py
fframelesswindow/titlebar/__init__.py
fframelesswindow/titlebar/title_bar_buttons.py
fframelesswindow/utils/__init__.py
fframelesswindow/utils/linux_utils.py
fframelesswindow/utils/mac_utils.py
fframelesswindow/utils/win32_utils.py
fframelesswindow/webengine/__init__.py
fframelesswindow/windows/__init__.py
fframelesswindow/windows/c_structures.py
fframelesswindow/windows/window_effect.py
python_fastui_window-1.0.2.dist-info/licenses/LICENSE
python_fastui_window-1.0.2.dist-info/METADATA
python_fastui_window-1.0.2.dist-info/WHEEL
python_fastui_window-1.0.2.dist-info/top_level.txt
python_fastui_window-1.0.2.dist-info/RECORD
